django_json_widget/__init__.py
django_json_widget/apps.py
django_json_widget/models.py
django_json_widget/urls.py
django_json_widget/views.py
django_json_widget/widgets.py
django_json_widget/static/css/django_json_widget.css
django_json_widget/static/dist/jsoneditor.min.css
django_json_widget/static/dist/jsoneditor.min.js
django_json_widget/static/dist/img/jsoneditor-icons.svg
django_json_widget/templates/django_json_widget.html
dj_json_widget-2.1.2.dist-info/AUTHORS.rst
dj_json_widget-2.1.2.dist-info/LICENSE
dj_json_widget-2.1.2.dist-info/METADATA
dj_json_widget-2.1.2.dist-info/WHEEL
dj_json_widget-2.1.2.dist-info/top_level.txt
dj_json_widget-2.1.2.dist-info/RECORD
